risma/__init__.py
risma/core.py
risma/main.py
risma-2025.7.dist-info/licenses/LICENSE
risma-2025.7.dist-info/METADATA
risma-2025.7.dist-info/WHEEL
risma-2025.7.dist-info/entry_points.txt
risma-2025.7.dist-info/top_level.txt
risma-2025.7.dist-info/RECORD
