Metadata-Version: 2.4
Name: RISMA
Version: 2025.7
Summary: Agriculture and Agri-Food Canada (AAFC)
Author-email: Morteza Khazaei <morteza.khazaei@usherbrooke.ca>
License:                                  Apache License
Project-URL: Homepage, https://github.com/Morteza-Khazaei/RISMA
Classifier: Programming Language :: Python :: 3
Classifier: License :: OSI Approved :: MIT License
Classifier: Operating System :: OS Independent
License-File: LICENSE
Requires-Dist: requests
Requires-Dist: pandas
Requires-Dist: lxml
Requires-Dist: matplotlib
Requires-Dist: ipykernel
Requires-Dist: click
Dynamic: license-file
